vkit/__init__.py
vkit/callbacks.py
vkit/lr.py
vkit/metrics.py
kit_vision-0.0.6.dist-info/LICENSE
kit_vision-0.0.6.dist-info/METADATA
kit_vision-0.0.6.dist-info/WHEEL
kit_vision-0.0.6.dist-info/top_level.txt
kit_vision-0.0.6.dist-info/RECORD
