Metadata-Version: 2.1
Name: kit-vision
Version: 0.0.6
Summary: Vision kit - Usefull tools for your computer vision project with TensorFlow
Home-page: https://github.com/mehrdad-dev/vision-kit
Author: Mehrdad Mohammdian
License: MIT
Platform: UNKNOWN
Classifier: Intended Audience :: Science/Research
Classifier: Intended Audience :: Developers
Classifier: Topic :: Software Development
Classifier: Topic :: Scientific/Engineering
Classifier: Programming Language :: Python :: 3
Classifier: Programming Language :: Python :: 3.8
Classifier: Programming Language :: Python :: 3.9
Classifier: Programming Language :: Python :: 3.10
Classifier: License :: OSI Approved :: MIT License
Classifier: Operating System :: OS Independent
Requires-Python: >=3.5
License-File: LICENSE
Requires-Dist: tensorflow (>=2.5.0)
Requires-Dist: matplotlib
Requires-Dist: numpy
